<?xml version="1.0"?>
<PropertyList>

<model>
  <path>Models/Effects/pos_lamp_red_light_2st.xml</path>
  <offsets>
    <x-m>-278.702</x-m>
    <y-m>-114.282</y-m>
    <z-m>59.1515</z-m>
    <pitch-deg> 0.00</pitch-deg>
    <heading-deg>0.0 </heading-deg>
  </offsets>
</model>

<model>
  <path>Models/Effects/pos_lamp_red_light_2st.xml</path>
  <offsets>
    <x-m>-287.72</x-m>
    <y-m>-114.746</y-m>
    <z-m>59.1515</z-m>
    <pitch-deg> 0.00</pitch-deg>
    <heading-deg>0.0 </heading-deg>
  </offsets>
</model>

<model>
  <path>Models/Effects/pos_lamp_red_light_2st.xml</path>
  <offsets>
    <x-m>-287.383</x-m>
    <y-m>-121.287</y-m>
    <z-m>59.1515</z-m>
    <pitch-deg> 0.00</pitch-deg>
    <heading-deg>0.0 </heading-deg>
  </offsets>
</model>

<model>
  <path>Models/Effects/pos_lamp_red_light_2st.xml</path>
  <offsets>
    <x-m>-278.366</x-m>
    <y-m>-120.799</y-m>
    <z-m>59.1515</z-m>
    <pitch-deg> 0.00</pitch-deg>
    <heading-deg>0.0 </heading-deg>
  </offsets>
</model>
</PropertyList>
